media2tex/__init__.py
media2tex/media2tex.py
media2tex/py.typed
media2tex-0.1.2.dist-info/WHEEL
media2tex-0.1.2.dist-info/METADATA
media2tex-0.1.2.dist-info/RECORD
