Metadata-Version: 2.3
Name: media2tex
Version: 0.1.2
Summary: A library which converts 2D arrays and image paths into valid LaTeX code
Author: Amir Gizzatullin
Author-email: Amir Gizzatullin <amirgizzatullin7777@gmail.com>
Requires-Python: >=3.12
